gpt4docs/MainApplication.py
gpt4docs/__init__.py
gpt4docs/__main__.py
gpt4docs/logger_config.py
gpt4docs/model/DocstringLLM.py
gpt4docs/model/ReadmeLLM.py
gpt4docs/model/__init__.py
gpt4docs/model/prompts/map.txt
gpt4docs/model/prompts/qa.txt
gpt4docs/model/prompts/readme.txt
gpt4docs/modules/__init__.py
gpt4docs/modules/datamodels/PyDefinition.py
gpt4docs/modules/datamodels/__init__.py
gpt4docs/modules/directory/File.py
gpt4docs/modules/directory/Project.py
gpt4docs/modules/directory/__init__.py
gpt4docs/modules/managers/LLMManager.py
gpt4docs/modules/managers/ProjectManager.py
gpt4docs/modules/managers/VectorStoreManager.py
gpt4docs/modules/managers/__init__.py
gpt4docs/scripts/build_vectorstore.py
gpt4docs-0.2.0.dist-info/LICENSE
gpt4docs-0.2.0.dist-info/METADATA
gpt4docs-0.2.0.dist-info/WHEEL
gpt4docs-0.2.0.dist-info/entry_points.txt
gpt4docs-0.2.0.dist-info/RECORD
